defweb/LICENSE
defweb/VERSION
defweb/__init__.py
defweb/__main__.py
defweb/main.py
defweb/proxy.py
defweb/reverse_proxy.py
defweb/version.py
defweb/webserver.py
defweb/common/__init__.py
defweb/common/constants.py
defweb/common/mapping_handlers.py
defweb/common/pki.py
defweb/errors/__init__.py
defweb/errors/base.py
defweb/errors/middleware_errors.py
defweb/handlers/__init__.py
defweb/handlers/proxy_tcp_handler.py
defweb/handlers/rev_proxy_http_handler.py
defweb/handlers/rev_proxy_tcp_handler.py
defweb/middlewares/__init__.py
defweb/middlewares/hex_dump.py
defweb/middlewares/http_log_requests.py
defweb/middlewares/http_save_session.py
defweb/middlewares/middleware_loader.py
defweb/objects/__init__.py
defweb/objects/middlewarebase.py
defweb/sources/user_agents.txt
defweb/utils/__init__.py
defweb/utils/logger_class.py
defweb-0.2.11.dist-info/METADATA
defweb-0.2.11.dist-info/WHEEL
defweb-0.2.11.dist-info/entry_points.txt
defweb-0.2.11.dist-info/top_level.txt
defweb-0.2.11.dist-info/RECORD
