Metadata-Version: 2.1
Name: defweb
Version: 0.2.11
Summary: Python webserver with https and upload support
Home-page: 
Author: Paul Tikken
Author-email: paul.tikken@gmail.com
License: GNU General Public License v3.0
Classifier: License :: OSI Approved :: GNU General Public License v3 or later (GPLv3+)
Classifier: Operating System :: POSIX :: Linux
Classifier: Programming Language :: Python
Classifier: Programming Language :: Python :: 3
Classifier: Programming Language :: Python :: 3.8
Requires-Python: >=3.8
Requires-Dist: ansicolors (==1.1.8)
